{"web":{"auth_uri":"https://accounts.google.com/o/oauth2/auth","client_secret":"N5zZRrQHT1LPm29ok6sWYzj1","token_uri":"https://accounts.google.com/o/oauth2/token","client_email":"19785738660-v1tikhnpih8c6jb7f2arp5lp03b0m756@developer.gserviceaccount.com","redirect_uris":["http://rbox.com:8000/oauth2/oauth2callback/"],"client_x509_cert_url":"https://www.googleapis.com/robot/v1/metadata/x509/19785738660-v1tikhnpih8c6jb7f2arp5lp03b0m756@developer.gserviceaccount.com","client_id":"19785738660-v1tikhnpih8c6jb7f2arp5lp03b0m756.apps.googleusercontent.com","auth_provider_x509_cert_url":"https://www.googleapis.com/oauth2/v1/certs","javascript_origins":["http://rbox.com:8000/"]}}
